greengrass_sod-0.0.1.dist-info/METADATA
greengrass_sod-0.0.1.dist-info/RECORD
greengrass_sod-0.0.1.dist-info/WHEEL
greengrass_sod-0.0.1.dist-info/top_level.txt
sod/__init__.py
tests/__init__.py
tests/test_greengrass_manager.py
