Metadata-Version: 2.1
Name: greengrass-sod
Version: 0.0.1
Summary: Easy Greengrass Scaffolding framework
Home-page: https://github.com/troylar/greengrass-sod
Author: Troy Larson
Author-email: troylar@gmail.com
License: UNKNOWN
Platform: UNKNOWN
Classifier: Programming Language :: Python :: 3
Classifier: License :: OSI Approved :: MIT License
Classifier: Operating System :: OS Independent
